quark_plugin_pvc/__init__.py
quark_plugin_pvc/createReferenceGraph.py
quark_plugin_pvc/greedy_classical_pvc_solver.py
quark_plugin_pvc/pvc_graph_provider.py
quark_plugin_pvc/pvc_qubo_mapping.py
quark_plugin_pvc/random_classical_pvc_solver.py
quark_plugin_pvc/reverse_greedy_classical_pvc_solver.py
quark_plugin_pvc/data/reference_data.txt
quark_plugin_pvc-0.1.6.dist-info/licenses/LICENSE
quark_plugin_pvc-0.1.6.dist-info/licenses/NOTICE
quark_plugin_pvc-0.1.6.dist-info/METADATA
quark_plugin_pvc-0.1.6.dist-info/WHEEL
quark_plugin_pvc-0.1.6.dist-info/top_level.txt
quark_plugin_pvc-0.1.6.dist-info/RECORD
